nonebot_plugin_wordbank/__init__.py
nonebot_plugin_wordbank/data_source.py
nonebot_plugin_wordbank/util.py
nonebot_plugin_wordbank-1.0.2.dist-info/LICENSE
nonebot_plugin_wordbank-1.0.2.dist-info/METADATA
nonebot_plugin_wordbank-1.0.2.dist-info/WHEEL
nonebot_plugin_wordbank-1.0.2.dist-info/top_level.txt
nonebot_plugin_wordbank-1.0.2.dist-info/RECORD
