Metadata-Version: 2.1
Name: nonebot-plugin-wordbank
Version: 1.0.2
Summary: 基于nonebot2的无数据库的轻量问答插件
Home-page: https://github.com/Joenothing-lst/word-bank
Author: Joenothing
Author-email: 912871833@qq.com
License: GPL-3.0 License
Platform: all
Classifier: Development Status :: 4 - Beta
Classifier: Operating System :: OS Independent
Classifier: Intended Audience :: Developers
Classifier: License :: OSI Approved :: GNU General Public License v3 (GPLv3)
Classifier: Programming Language :: Python
Classifier: Programming Language :: Python :: Implementation
Classifier: Programming Language :: Python :: 3
Classifier: Programming Language :: Python :: 3.6
Classifier: Programming Language :: Python :: 3.7
Classifier: Programming Language :: Python :: 3.8
Classifier: Topic :: Software Development :: Libraries
